aib2ynab/__init__.py
aib2ynab/__main__.py
aib2ynab/cli.py
aib2ynab-0.2.0.dist-info/LICENSE
aib2ynab-0.2.0.dist-info/METADATA
aib2ynab-0.2.0.dist-info/WHEEL
aib2ynab-0.2.0.dist-info/entry_points.txt
aib2ynab-0.2.0.dist-info/RECORD
