Metadata-Version: 2.1
Name: aib2ynab
Version: 0.2.0
Summary: Converts an exported file of historical transactions from an AIB Personal Online Banking account into a CSV format that you can import into your YNAB account.
Home-page: https://github.com/andyregan/aib2ynab
License: Apache-2.0
Keywords: aib,ynab
Author: Andrew Regan
Author-email: andrew@andyregan.net
Requires-Python: >=3.12,<4.0
Classifier: License :: OSI Approved :: Apache Software License
Classifier: Programming Language :: Python :: 3
Classifier: Programming Language :: Python :: 3.12
Requires-Dist: click (>=8.1.7,<9.0.0)
Project-URL: Repository, https://github.com/andyregan/aib2ynab
